mrc_engine/__init__.py
mrc_engine/common_pb2.py
mrc_engine/common_pb2_grpc.py
mrc_engine/grpc_client.py
mrc_engine/models.py
mrc_engine/mrcEngine_pb2.py
mrc_engine/mrcEngine_pb2_grpc.py
longleding_mrc_engine_sdk-0.1.1.dist-info/LICENSE
longleding_mrc_engine_sdk-0.1.1.dist-info/METADATA
longleding_mrc_engine_sdk-0.1.1.dist-info/WHEEL
longleding_mrc_engine_sdk-0.1.1.dist-info/top_level.txt
longleding_mrc_engine_sdk-0.1.1.dist-info/RECORD
